odoo/addons/fieldservice_logbook/README.rst
odoo/addons/fieldservice_logbook/__init__.py
odoo/addons/fieldservice_logbook/__manifest__.py
odoo/addons/fieldservice_logbook/i18n/fieldservice_logbook.pot
odoo/addons/fieldservice_logbook/models/__init__.py
odoo/addons/fieldservice_logbook/models/fsm_equipment.py
odoo/addons/fieldservice_logbook/models/fsm_equipment_logbook.py
odoo/addons/fieldservice_logbook/models/fsm_equipment_logbook_mixin.py
odoo/addons/fieldservice_logbook/models/fsm_location.py
odoo/addons/fieldservice_logbook/models/fsm_order.py
odoo/addons/fieldservice_logbook/readme/CONTRIBUTORS.md
odoo/addons/fieldservice_logbook/readme/DESCRIPTION.md
odoo/addons/fieldservice_logbook/security/ir.model.access.csv
odoo/addons/fieldservice_logbook/security/res_groups.xml
odoo/addons/fieldservice_logbook/static/description/icon.png
odoo/addons/fieldservice_logbook/static/description/index.html
odoo/addons/fieldservice_logbook/tests/__init__.py
odoo/addons/fieldservice_logbook/tests/test_fsm_equipment_logbook.py
odoo/addons/fieldservice_logbook/views/fsm_equipment.xml
odoo/addons/fieldservice_logbook/views/fsm_equipment_logbook.xml
odoo/addons/fieldservice_logbook/views/fsm_location.xml
odoo/addons/fieldservice_logbook/views/fsm_order.xml
odoo_addon_fieldservice_logbook-15.0.1.0.0.2.dist-info/METADATA
odoo_addon_fieldservice_logbook-15.0.1.0.0.2.dist-info/WHEEL
odoo_addon_fieldservice_logbook-15.0.1.0.0.2.dist-info/top_level.txt
odoo_addon_fieldservice_logbook-15.0.1.0.0.2.dist-info/RECORD
